Metadata-Version: 2.4
Name: llama-index-readers-stackoverflow
Version: 0.4.1
Summary: llama-index readers stackoverflow integration
Author-email: Your Name <you@example.com>
Maintainer: allen-munsch
License-Expression: MIT
License-File: LICENSE
Keywords: answers,posts,questions
Requires-Python: <4.0,>=3.9
Requires-Dist: llama-index-core<0.15,>=0.13.0
Requires-Dist: requests<3,>=2.31.0
